design.sv
module cache_controller_4way (
    input  clk, rst,

    // CPU Port
    input  cpu_req, cpu_rw,      // 0: Read, 1: Write
    input  wire [31:0] cpu_addr, cpu_wdata,
    output reg         cpu_ready,
    output reg  [31:0] cpu_rdata,

    // Main Memory Port
    output reg         mem_req, mem_rw,      // 0: Read, 1: Write
    output reg  [31:0] mem_addr,
    output reg  [127:0] mem_wdata,
    input  wire        mem_ready,
    input  wire [127:0] mem_rdata
);

    // 1. Parameters & Address Decoding
    localparam SETS = 256;
    wire [19:0] cpu_tag    = cpu_addr[31:12];
    wire [7:0]  cpu_index  = cpu_addr[11:4];
    wire [3:0]  cpu_offset = cpu_addr[3:0]; // 16 bytes per line

    // FSM States
    localparam IDLE       = 2'b00;
    localparam COMPARE    = 2'b01;
    localparam ALLOCATE   = 2'b10;
    localparam WRITE_BACK = 2'b11;

    // 2. Cache Memory Arrays (4 Ways)
    reg         valid_array [0:3][0:SETS-1];
    reg         dirty_array [0:3][0:SETS-1];
    reg [19:0]  tag_array   [0:3][0:SETS-1];
    reg [127:0] data_array  [0:3][0:SETS-1];
    
    // Round-Robin Replacement Pointer (0 to 3) for each set
    reg [1:0]   rr_ptr      [0:SETS-1]; 

    reg [1:0] state, next_state;
    integer i;

    // 3. Datapath: Hit Detection Logic
    wire hit_0 = valid_array[0][cpu_index] & (tag_array[0][cpu_index] == cpu_tag);
    wire hit_1 = valid_array[1][cpu_index] & (tag_array[1][cpu_index] == cpu_tag);
    wire hit_2 = valid_array[2][cpu_index] & (tag_array[2][cpu_index] == cpu_tag);
    wire hit_3 = valid_array[3][cpu_index] & (tag_array[3][cpu_index] == cpu_tag);

    wire cache_hit = hit_0 | hit_1 | hit_2 | hit_3;

    wire [1:0] hit_way = hit_0 ? 2'd0 :
                         hit_1 ? 2'd1 :
                         hit_2 ? 2'd2 : 2'd3;

    wire [1:0] victim_way = rr_ptr[cpu_index];
    wire victim_dirty     = dirty_array[victim_way][cpu_index];

    wire [127:0] hit_data_block = data_array[hit_way][cpu_index];

    // 4. Sequential Logic: State Register ONLY
    always @(posedge clk or posedge rst) begin
        if (rst) begin
            state <= IDLE;
        end else begin
            state <= next_state;
        end
    end

    // 5. Combinational Logic: FSM Next State & Outputs
    always @(*) begin
        next_state = state;
        cpu_ready  = 1'b0;
        mem_req    = 1'b0;
        mem_rw     = 1'b0;
        mem_addr   = 32'd0;
        mem_wdata  = 128'd0;
        cpu_rdata  = 32'd0;
        
        case(cpu_offset[3:2])
            2'b00: cpu_rdata = hit_data_block[31:0];
            2'b01: cpu_rdata = hit_data_block[63:32];
            2'b10: cpu_rdata = hit_data_block[95:64];
            2'b11: cpu_rdata = hit_data_block[127:96];
        endcase

        case (state)
            IDLE: begin
                if (cpu_req) next_state = COMPARE;
            end

            COMPARE: begin
                if (cache_hit) begin
                    cpu_ready  = 1'b1;
                    next_state = IDLE;
                end else begin
                    if (victim_dirty) begin
                        next_state = WRITE_BACK;
                    end else begin
                        next_state = ALLOCATE;
                    end
                end
            end

            ALLOCATE: begin
                mem_req  = 1'b1;
                mem_rw   = 1'b0; 
                mem_addr = {cpu_tag, cpu_index, 4'b0000}; 
                
                if (mem_ready) next_state = COMPARE; 
            end

            WRITE_BACK: begin
                mem_req   = 1'b1;
                mem_rw    = 1'b1; 
                mem_addr  = {tag_array[victim_way][cpu_index], cpu_index, 4'b0000};
                mem_wdata = data_array[victim_way][cpu_index];
                
                if (mem_ready) next_state = ALLOCATE; 
            end
        endcase
    end

    // 6. Sequential Logic: Memory Array Updates
    always @(posedge clk or posedge rst) begin
        if (rst) begin
            for (i = 0; i < SETS; i = i + 1) begin
                valid_array[0][i] <= 0; valid_array[1][i] <= 0;
                valid_array[2][i] <= 0; valid_array[3][i] <= 0;
                dirty_array[0][i] <= 0; dirty_array[1][i] <= 0;
                dirty_array[2][i] <= 0; dirty_array[3][i] <= 0;
                rr_ptr[i] <= 2'd0;
            end
        end else begin
            // Handle Write Hit
            if (state == COMPARE && cache_hit && cpu_rw == 1'b1) begin
                dirty_array[hit_way][cpu_index] <= 1'b1;
                case(cpu_offset[3:2])
                    2'b00: data_array[hit_way][cpu_index][31:0]   <= cpu_wdata;
                    2'b01: data_array[hit_way][cpu_index][63:32]  <= cpu_wdata;
                    2'b10: data_array[hit_way][cpu_index][95:64]  <= cpu_wdata;
                    2'b11: data_array[hit_way][cpu_index][127:96] <= cpu_wdata;
                endcase
            end
            
            // Handle ALLOCATE 
            if (state == ALLOCATE && mem_ready) begin
                data_array[victim_way][cpu_index]  <= mem_rdata;
                tag_array[victim_way][cpu_index]   <= cpu_tag;
                valid_array[victim_way][cpu_index] <= 1'b1;
                dirty_array[victim_way][cpu_index] <= 1'b0;
                rr_ptr[cpu_index] <= rr_ptr[cpu_index] + 1; 
            end
        end
    end

endmodule

testbench.sv
`timescale 1ns / 1ps

module tb_cache_controller();

    // Signals
    reg clk;
    reg rst;

    // CPU Signals
    reg         cpu_req;
    reg         cpu_rw;
    reg  [31:0] cpu_addr;
    reg  [31:0] cpu_wdata;
    wire        cpu_ready;
    wire [31:0] cpu_rdata;

    // Memory Signals
    wire         mem_req;
    wire         mem_rw;
    wire [31:0]  mem_addr;
    wire [127:0] mem_wdata;
    reg          mem_ready;
    reg  [127:0] mem_rdata;

    // Instantiate DUT
    cache_controller_4way uut (
        .clk(clk), .rst(rst),
        .cpu_req(cpu_req), .cpu_rw(cpu_rw),
        .cpu_addr(cpu_addr), .cpu_wdata(cpu_wdata),
        .cpu_ready(cpu_ready), .cpu_rdata(cpu_rdata),
        .mem_req(mem_req), .mem_rw(mem_rw),
        .mem_addr(mem_addr), .mem_wdata(mem_wdata),
        .mem_ready(mem_ready), .mem_rdata(mem_rdata)
    );

    // Clock
    always #5 clk = ~clk;

    // Mock Main Memory
    always @(posedge clk) begin
        if (rst) begin
            mem_ready <= 1'b0;
            mem_rdata <= 128'd0;
        end else if (mem_req && !mem_ready) begin
            #20; // simulate delay
            mem_ready <= 1'b1;
            mem_rdata <= {32'hCAFEBABE, 32'hCAFEBABE, 32'hCAFEBABE, 32'hCAFEBABE};
        end else if (!mem_req) begin
            mem_ready <= 1'b0;
        end
    end

    // Test Sequence
    initial begin
        $dumpfile("dump.vcd");
        $dumpvars(0, tb_cache_controller);
        
        clk = 0; rst = 1;
        cpu_req = 0; cpu_rw = 0; cpu_addr = 0; cpu_wdata = 0;

        #20 rst = 0;
        #10;

        $display("--- TEST 1: CPU Write Miss ---");
        @(posedge clk);
        cpu_req   = 1;
        cpu_rw    = 1; 
        cpu_addr  = 32'h0000_1000;
        cpu_wdata = 32'hDEADBEEF;

        wait(cpu_ready == 1'b1);
        @(posedge clk);
        cpu_req = 0; 
        $display("Test 1 Complete. Wrote DEADBEEF to Cache.");
        #20;

        $display("--- TEST 2: CPU Read Hit ---");
        @(posedge clk);
        cpu_req  = 1;
        cpu_rw   = 0; 
        cpu_addr = 32'h0000_1000;

        wait(cpu_ready == 1'b1);
        $display("Test 2 Complete. Read Data: %h (Expected: DEADBEEF)", cpu_rdata);
        @(posedge clk);
        cpu_req = 0;
        #20;

        $display("--- TEST 3: CPU Read Miss ---");
        @(posedge clk);
        cpu_req  = 1;
        cpu_rw   = 0; 
        cpu_addr = 32'h0000_2000;

        wait(cpu_ready == 1'b1);
        $display("Test 3 Complete. Read Data: %h (Expected: CAFEBABE)", cpu_rdata);
        @(posedge clk);
        cpu_req = 0;
        #20;

        $display("--- ALL TESTS FINISHED ---");
        $finish;
    end
endmodule

dump.vcd
$version Generated by VerilatedVcd $end
$timescale 1ps $end
 $scope module tb_cache_controller $end
  $var wire 1 E clk $end
  $var wire 1 # rst $end
  $var wire 1 $ cpu_req $end
  $var wire 1 % cpu_rw $end
  $var wire 32 & cpu_addr [31:0] $end
  $var wire 32 ' cpu_wdata [31:0] $end
  $var wire 1 + cpu_ready $end
  $var wire 32 F cpu_rdata [31:0] $end
  $var wire 1 < mem_req $end
  $var wire 1 = mem_rw $end
  $var wire 32 , mem_addr [31:0] $end
  $var wire 128 - mem_wdata [127:0] $end
  $var wire 1 @ mem_ready $end
  $var wire 128 A mem_rdata [127:0] $end
  $scope module uut $end
   $var wire 1 E clk $end
   $var wire 1 # rst $end
   $var wire 1 $ cpu_req $end
   $var wire 1 % cpu_rw $end
   $var wire 32 & cpu_addr [31:0] $end
   $var wire 32 ' cpu_wdata [31:0] $end
   $var wire 1 + cpu_ready $end
   $var wire 32 F cpu_rdata [31:0] $end
   $var wire 1 < mem_req $end
   $var wire 1 = mem_rw $end
   $var wire 32 , mem_addr [31:0] $end
   $var wire 128 - mem_wdata [127:0] $end
   $var wire 1 @ mem_ready $end
   $var wire 128 A mem_rdata [127:0] $end
   $var wire 32 I SETS [31:0] $end
   $var wire 20 ( cpu_tag [19:0] $end
   $var wire 8 ) cpu_index [7:0] $end
   $var wire 4 * cpu_offset [3:0] $end
   $var wire 2 J IDLE [1:0] $end
   $var wire 2 K COMPARE [1:0] $end
   $var wire 2 L ALLOCATE [1:0] $end
   $var wire 2 M WRITE_BACK [1:0] $end
   $var wire 2 > state [1:0] $end
   $var wire 2 1 next_state [1:0] $end
   $var wire 32 ? i [31:0] $end
   $var wire 1 2 hit_0 $end
   $var wire 1 3 hit_1 $end
   $var wire 1 4 hit_2 $end
   $var wire 1 G hit_3 $end
   $var wire 1 5 cache_hit $end
   $var wire 2 6 hit_way [1:0] $end
   $var wire 2 7 victim_way [1:0] $end
   $var wire 1 H victim_dirty $end
   $var wire 128 8 hit_data_block [127:0] $end
  $upscope $end
 $upscope $end
$enddefinitions $end


#0
1#
0$
0%
b00000000000000000000000000000000 &
b00000000000000000000000000000000 '
b00000000000000000000 (
b00000000 )
b0000 *
0+
b00000000000000000000000000000000 ,
b00000000000000000000000000000000000000000000000000000000000000000000000000000000000000000000000000000000000000000000000000000000 -
b00 1
02
03
04
05
b11 6
b00 7
b00000000000000000000000000000000000000000000000000000000000000000000000000000000000000000000000000000000000000000000000000000000 8
0<
0=
b00 >
b00000000000000000000000100000000 ?
0@
b00000000000000000000000000000000000000000000000000000000000000000000000000000000000000000000000000000000000000000000000000000000 A
0E
b00000000000000000000000000000000 F
0G
0H
b00000000000000000000000100000000 I
b00 J
b01 K
b10 L
b11 M
#5000
1E
#10000
0E
#15000
1E
#20000
0#
0E
#25000
1E
#30000
0E
#35000
1$
1%
b00000000000000000001000000000000 &
b11011110101011011011111011101111 '
b00000000000000000001 (
b10 1
b01 >
1E
#40000
0E
#45000
b00000000000000000001000000000000 ,
1<
b10 >
1E
#50000
0E
#55000
1E
#60000
0E
#65000
1E
#70000
0E
#75000
b01 1
1@
b11001010111111101011101010111110110010101111111010111010101111101100101011111110101110101011111011001010111111101011101010111110 A
1E
#80000
0E
#85000
1+
b00000000000000000000000000000000 ,
b00 1
12
15
b00 6
b01 7
b11001010111111101011101010111110110010101111111010111010101111101100101011111110101110101011111011001010111111101011101010111110 8
0<
b01 >
1E
b11001010111111101011101010111110 F
#90000
0E
#95000
0$
0+
b11001010111111101011101010111110110010101111111010111010101111101100101011111110101110101011111011011110101011011011111011101111 8
b00 >
0@
1E
b11011110101011011011111011101111 F
#100000
0E
#105000
1E
#110000
0E
#115000
1E
#120000
0E
#125000
1$
0%
1+
b01 >
1E
#130000
0E
#135000
0$
0+
b00 >
1E
#140000
0E
#145000
1E
#150000
0E
#155000
1E
#160000
0E
#165000
1$
b00000000000000000010000000000000 &
b00000000000000000010 (
b10 1
02
05
b11 6
b00000000000000000000000000000000000000000000000000000000000000000000000000000000000000000000000000000000000000000000000000000000 8
b01 >
1E
b00000000000000000000000000000000 F
#170000
0E
#175000
b00000000000000000010000000000000 ,
1<
b10 >
1E
#180000
0E
#185000
1E
#190000
0E
#195000
1E
#200000
0E
#205000
b01 1
1@
1E
#210000
0E
#215000
1+
b00000000000000000000000000000000 ,
b00 1
13
15
b01 6
b10 7
b11001010111111101011101010111110110010101111111010111010101111101100101011111110101110101011111011001010111111101011101010111110 8
0<
b01 >
1E
b11001010111111101011101010111110 F
#220000
0E
#225000
0$
0+
b00 >
0@
1E
