design.sv
// Code your design here
module cache_controller_4way (
    input  clk, rst,

    // CPU Port
    input  cpu_req, cpu_rw,      // 0: Read, 1: Write
    input  [31:0] cpu_addr, cpu_wdata,
    output reg cpu_ready,
    output reg  [31:0] cpu_rdata,

    // Main Memory Port
    output reg  mem_req, mem_rw, // 0: Read, 1: Write
    output reg [31:0] mem_addr,
    output reg [127:0] mem_wdata,
    input   mem_ready,
    input [127:0] mem_rdata
);

    localparam SETS = 256;
    wire [19:0] cpu_tag    = cpu_addr[31:12];
    wire [7:0]  cpu_index  = cpu_addr[11:4];
    wire [3:0]  cpu_offset = cpu_addr[3:0]; // 16 bytes per line

    // FSM States
    localparam IDLE       = 2'b00;
    localparam COMPARE    = 2'b01;
    localparam ALLOCATE   = 2'b10;
    localparam WRITE_BACK = 2'b11;
  
  
    reg valid_array [0:3][0:SETS-1];
    reg dirty_array [0:3][0:SETS-1];
    reg [19:0]  tag_array [0:3][0:SETS-1];
    reg [127:0] data_array  [0:3][0:SETS-1];
    
    // Round-Robin Pointer
    reg [1:0]rr_ptr[0:SETS-1]; 

    // State Flip-Flops
    reg [1:0] state, next_state;
    integer i;
  
  wire hit0=valid_array[0][cpu_index] && tag_array[0][cpu_index]==cpu_tag;
  wire hit1=valid_array[1][cpu_index] && tag_array[1][cpu_index]==cpu_tag;
  wire hit2=valid_array[2][cpu_index] && tag_array[2][cpu_index]==cpu_tag;
  wire hit3=valid_array[3][cpu_index] && tag_array[3][cpu_index]==cpu_tag;
  
  wire hit=hit0|hit1|hit2|hit3;
  wire [1:0] hit_way=hit0?0:hit1?1:hit2?2:3;
  wire [127:0] hit_block=data_array[hit_way][cpu_index];
  
  wire dirty=dirty_array[rr_ptr[cpu_index]][cpu_index];
  
  always@(*)
    begin
    case(cpu_offset[3:2])
      0:cpu_rdata=hit_block[31:0];
      1:cpu_rdata=hit_block[63:32];
      2:cpu_rdata=hit_block[95:64];
      3:cpu_rdata=hit_block[127:96];
  endcase
    end
  
  always@(posedge clk or posedge rst)
    begin
      if(rst) begin
        state=IDLE;
        for(i=0;i< SETS;i++) begin
          valid_array[0][i]<= 0;
          valid_array[1][i]<= 0;
          valid_array[2][i]<= 0;
          valid_array[3][i] <= 0;
           dirty_array[0][i] <= 0;
          dirty_array[1][i] <= 0;
            dirty_array[2][i] <= 0;
          dirty_array[3][i] <= 0;
                rr_ptr[i] <= 0;
        end
      end
        else begin
          state<=next_state;
          
      if (state == COMPARE&&hit &&cpu_rw == 1'b1) begin
                dirty_array[hit_way][cpu_index] <= 1'b1;
                case(cpu_offset[3:2])
                    0: data_array[hit_way][cpu_index][31:0] <=cpu_wdata;
                    1: data_array[hit_way][cpu_index][63:32]<= cpu_wdata;
                    2: data_array[hit_way][cpu_index][95:64]<= cpu_wdata;
                    3: data_array[hit_way][cpu_index][127:96]<=cpu_wdata;
                endcase
            end
            
            // Handle ALLOCATE 
            if (state == ALLOCATE && mem_ready) begin
                data_array[rr_ptr[cpu_index]][cpu_index] <= mem_rdata;
              tag_array[rr_ptr[cpu_index]][cpu_index]<=cpu_tag;
              valid_array[rr_ptr[cpu_index]][cpu_index]<=1;
              dirty_array[rr_ptr[cpu_index]][cpu_index]<=0;
              rr_ptr[cpu_index]<=rr_ptr[cpu_index]+1;
            end
           
        end
    end
    
  always@(*)
    begin
      next_state=state;
      mem_req=0;
      mem_rw=0;
      cpu_ready=0;
      mem_addr=0;
      mem_wdata=0;
      
      case(state)
        IDLE:if(cpu_req)
            next_state=COMPARE;
        COMPARE:begin
          if(hit)
          begin
            cpu_ready=1;
            next_state=IDLE;
          end
            else if(dirty)
              next_state=WRITE_BACK;
            else
              next_state=ALLOCATE;
        end
        
        
    WRITE_BACK:begin
        mem_req=1;
        mem_rw=1;
        mem_wdata=data_array[rr_ptr[cpu_index]][cpu_index];
        mem_addr= {tag_array[rr_ptr[cpu_index]][cpu_index], cpu_index, 4'b0000};
                
         if (mem_ready) next_state = ALLOCATE; 
        end
        
          ALLOCATE:begin
          mem_req=1;
          mem_rw=0;
          mem_addr= {tag_array[rr_ptr[cpu_index]][cpu_index], cpu_index, 4'b0000};
          
          if (mem_ready) next_state = COMPARE;
            end
        endcase
    end
endmodule

testbench.sv
`timescale 1ns/1ps

module tb_cache_controller;

    // 1. Signals
    reg clk, rst;
    
    // CPU Signals
    reg   cpu_req, cpu_rw;
    reg  [31:0] cpu_addr, cpu_wdata;
    wire  cpu_ready;
    wire [31:0] cpu_rdata;
    
    // Memory Signals
    wire   mem_req, mem_rw;
    wire [31:0]  mem_addr;
    wire [127:0] mem_wdata;
    reg    mem_ready;
    reg  [127:0] mem_rdata;

    // 2. Instantiate the DUT (Device Under Test)
    cache_controller_4way dut (
        .clk(clk),.rst(rst),
        .cpu_req(cpu_req),.cpu_rw(cpu_rw),.cpu_addr(cpu_addr),
        .cpu_wdata(cpu_wdata),.cpu_ready(cpu_ready),
        .cpu_rdata(cpu_rdata),
      .mem_req(mem_req),
        .mem_rw(mem_rw),
        .mem_addr(mem_addr),
           .mem_wdata(mem_wdata),
           .mem_ready(mem_ready),
        .mem_rdata(mem_rdata)
    );

    // 3. Clock Generation (100 MHz)
    initial clk = 0;
    always #5 clk = ~clk;

    // 4. Dummy Main Memory Model (Cycle-Accurate)
    always @(posedge clk) begin
        if (rst) begin
            mem_ready <= 0;
            mem_rdata <= 0;
        end else begin
            if (mem_req && !mem_ready) begin
                // Simulate DRAM latency: Wait 3 clock cycles
                repeat(3) @(posedge clk);
                
                mem_ready <= 1;
                
                // If Read Request, send dummy 128-bit block
                if (!mem_rw) begin
                    // Sending 4 distinct 32-bit words so you can see the offset MUX working
                    mem_rdata <= {32'h44444444, 32'h33333333, 32'h22222222, 32'h11111111};
                end
            end else begin
                // Drop ready signal once transaction is complete
                mem_ready <= 0;
            end
        end
    end

    // 5. Stimulus (The CPU)
    initial begin
        // Required for EDA Playground Waveforms
        $dumpfile("dump.vcd");
        $dumpvars(0, tb_cache_controller);

        // Initialize CPU signals
        rst = 1;
        cpu_req = 0;
        cpu_rw = 0;
        cpu_addr = 0;
        cpu_wdata = 0;

        // Release Reset
        repeat(2) @(posedge clk);
        rst = 0;
        repeat(2) @(posedge clk);

        // TEST 1: Read Miss (Compulsory Miss)
        // Address: Tag=0x00010, Index=0x00, Offset=0x0
        $display("[%0t] TEST 1: CPU Read Miss", $time);
        @(posedge clk);
        cpu_req = 1;
        cpu_rw  = 0;
        cpu_addr = 32'h1000_0000;
        
        // Wait for handshake
        wait(cpu_ready == 1);
        @(posedge clk);
        $display("[%0t] TEST 1 COMPLETE: Cache returned data: %h", $time, cpu_rdata);
        cpu_req = 0; // Drop request
        repeat(2) @(posedge clk);

        // TEST 2: Read Hit 
        // Read exact same address, should hit instantly
        $display("[%0t] TEST 2: CPU Read Hit", $time);
        @(posedge clk);
        cpu_req = 1;
        cpu_rw  = 0;
        cpu_addr = 32'h1000_0000;
        
        wait(cpu_ready == 1);
        @(posedge clk);
        $display("[%0t] TEST 2 COMPLETE: Cache returned data: %h", $time, cpu_rdata);
        cpu_req = 0;
        repeat(2) @(posedge clk);
        // TEST 3: Write Hit
        // Write to offset 0x4 (2nd word of the line)
        $display("[%0t] TEST 3: CPU Write Hit", $time);
        @(posedge clk);
        cpu_req = 1;
        cpu_rw  = 1; // Write mode
        cpu_addr = 32'h1000_0004; // Offset is 4
        cpu_wdata = 32'hDEADBEEF;
        
        wait(cpu_ready == 1);
        @(posedge clk);
        $display("[%0t] TEST 3 COMPLETE: Wrote %h to cache", $time, cpu_wdata);
        cpu_req = 0;
        
        // End simulation
        repeat(5) @(posedge clk);
        $display("[%0t] Simulation Finished.", $time);
        $finish;
    end

endmodule

dump.vcd
$date
	Thu Aug 20 06:42:20 2026
$end
$version
	Icarus Verilog
$end
$timescale
	1ps
$end
$scope module tb_cache_controller $end
$var wire 128 ! mem_wdata [127:0] $end
$var wire 1 " mem_rw $end
$var wire 1 # mem_req $end
$var wire 32 $ mem_addr [31:0] $end
$var wire 1 % cpu_ready $end
$var wire 32 & cpu_rdata [31:0] $end
$var reg 1 ' clk $end
$var reg 32 ( cpu_addr [31:0] $end
$var reg 1 ) cpu_req $end
$var reg 1 * cpu_rw $end
$var reg 32 + cpu_wdata [31:0] $end
$var reg 128 , mem_rdata [127:0] $end
$var reg 1 - mem_ready $end
$var reg 1 . rst $end
$scope module dut $end
$var wire 1 ' clk $end
$var wire 32 / cpu_addr [31:0] $end
$var wire 1 ) cpu_req $end
$var wire 1 * cpu_rw $end
$var wire 32 0 cpu_wdata [31:0] $end
$var wire 1 1 dirty $end
$var wire 1 2 hit $end
$var wire 1 3 hit0 $end
$var wire 1 4 hit1 $end
$var wire 1 5 hit2 $end
$var wire 1 6 hit3 $end
$var wire 128 7 hit_block [127:0] $end
$var wire 128 8 mem_rdata [127:0] $end
$var wire 1 - mem_ready $end
$var wire 1 . rst $end
$var wire 2 9 hit_way [1:0] $end
$var wire 20 : cpu_tag [19:0] $end
$var wire 4 ; cpu_offset [3:0] $end
$var wire 8 < cpu_index [7:0] $end
$var parameter 2 = ALLOCATE $end
$var parameter 2 > COMPARE $end
$var parameter 2 ? IDLE $end
$var parameter 32 @ SETS $end
$var parameter 2 A WRITE_BACK $end
$var reg 32 B cpu_rdata [31:0] $end
$var reg 1 % cpu_ready $end
$var reg 32 C mem_addr [31:0] $end
$var reg 1 # mem_req $end
$var reg 1 " mem_rw $end
$var reg 128 D mem_wdata [127:0] $end
$var reg 2 E next_state [1:0] $end
$var reg 2 F state [1:0] $end
$var integer 32 G i [31:0] $end
$upscope $end
$upscope $end
$enddefinitions $end
$comment Show the parameter values. $end
$dumpall
b11 A
b100000000 @
b0 ?
b1 >
b10 =
$end
#0
$dumpvars
b100000000 G
b0 F
b0 E
b0 D
b0 C
bx B
b0 <
b0 ;
b0 :
b11 9
bx 8
bx 7
06
05
04
03
02
01
b0 0
b0 /
1.
x-
bx ,
b0 +
0*
0)
b0 (
0'
bx &
0%
b0 $
0#
0"
b0 !
$end
#5000
b0 ,
b0 8
0-
b100000000 G
1'
#10000
0'
#15000
0.
1'
#20000
0'
#25000
1'
#30000
0'
#35000
1'
#40000
0'
#45000
b10000000000000000 :
b1 E
b10000000000000000000000000000 (
b10000000000000000000000000000 /
1)
1'
#50000
0'
#55000
b10 E
b1 F
1'
#60000
0'
#65000
bx000000000000 $
bx000000000000 C
1#
b10 F
1'
#70000
0'
#75000
1'
#80000
0'
#85000
1'
#90000
0'
#95000
1'
#100000
0'
#105000
b1 E
bx000000000000 $
bx000000000000 C
1#
b1000100010001000100010001000100001100110011001100110011001100110010001000100010001000100010001000010001000100010001000100010001 ,
b1000100010001000100010001000100001100110011001100110011001100110010001000100010001000100010001000010001000100010001000100010001 8
1-
1'
#110000
0'
#115000
1%
12
b10001000100010001000100010001 &
b10001000100010001000100010001 B
b1000100010001000100010001000100001100110011001100110011001100110010001000100010001000100010001000010001000100010001000100010001 7
b0 9
13
b0 E
b0 $
b0 C
0#
b1 F
0-
1'
#120000
0'
#125000
b0 F
0%
b0 E
0)
1'
#130000
0'
#135000
1'
#140000
0'
#145000
1'
#150000
0'
#155000
b1 E
1)
1'
#160000
0'
#165000
b0 E
1%
b1 F
1'
#170000
0'
#175000
b0 F
0%
b0 E
0)
1'
#180000
0'
#185000
1'
#190000
0'
#195000
1'
#200000
0'
#205000
b100010001000100010001000100010 &
b100010001000100010001000100010 B
b100 ;
b1 E
b11011110101011011011111011101111 +
b11011110101011011011111011101111 0
b10000000000000000000000000100 (
b10000000000000000000000000100 /
1*
1)
1'
#210000
0'
#215000
b0 E
1%
b1 F
1'
#220000
0'
#225000
b11011110101011011011111011101111 &
b11011110101011011011111011101111 B
b1000100010001000100010001000100001100110011001100110011001100111101111010101101101111101110111100010001000100010001000100010001 7
b0 F
0%
b0 E
0)
1'
